{
   "Afghanistan":{
      "rankingPts":991.19,
      "confederationID":"AFC",
      "flagCode":"af"
   },
   "Albania":{
      "rankingPts":1401.07,
      "confederationID":"UEFA",
      "flagCode":"al"
   },
   "Algeria":{
      "rankingPts":1516.37,
      "confederationID":"CAF",
      "flagCode":"dz"
   },
   "American Samoa":{
      "rankingPts":883.17,
      "confederationID":"OFC",
      "flagCode":"as"
   },
   "Andorra":{
      "rankingPts":949.44,
      "confederationID":"UEFA",
      "flagCode":"ad"
   },
   "Angola":{
      "rankingPts":1271.54,
      "confederationID":"CAF",
      "flagCode":"ao"
   },
   "Anguilla":{
      "rankingPts":759.78,
      "confederationID":"CONCACAF",
      "flagCode":"ai"
   },
   "Antigua and Barbuda":{
      "rankingPts":986.58,
      "confederationID":"CONCACAF",
      "flagCode":"ag"
   },
   "Argentina":{
      "rankingPts":1873.33,
      "confederationID":"CONMEBOL",
      "flagCode":"ar"
   },
   "Armenia":{
      "rankingPts":1196.08,
      "confederationID":"UEFA",
      "flagCode":"am"
   },
   "Aruba":{
      "rankingPts":867.94,
      "confederationID":"CONCACAF",
      "flagCode":"aw"
   },
   "Australia":{
      "rankingPts":1570.21,
      "confederationID":"AFC",
      "flagCode":"au"
   },
   "Austria":{
      "rankingPts":1585.51,
      "confederationID":"UEFA",
      "flagCode":"at"
   },
   "Azerbaijan":{
      "rankingPts":1132.97,
      "confederationID":"UEFA",
      "flagCode":"az"
   },
   "Bahamas":{
      "rankingPts":796.6,
      "confederationID":"CONCACAF",
      "flagCode":"bs"
   },
   "Bahrain":{
      "rankingPts":1254.48,
      "confederationID":"AFC",
      "flagCode":"bh"
   },
   "Bangladesh":{
      "rankingPts":911.19,
      "confederationID":"AFC",
      "flagCode":"bd"
   },
   "Barbados":{
      "rankingPts":914.42,
      "confederationID":"CONCACAF",
      "flagCode":"bb"
   },
   "Belarus":{
      "rankingPts":1227.09,
      "confederationID":"UEFA",
      "flagCode":"by"
   },
   "Belgium":{
      "rankingPts":1730.71,
      "confederationID":"UEFA",
      "flagCode":"be"
   },
   "Belize":{
      "rankingPts":910.74,
      "confederationID":"CONCACAF",
      "flagCode":"bz"
   },
   "Benin":{
      "rankingPts":1255.72,
      "confederationID":"CAF",
      "flagCode":"bj"
   },
   "Bermuda":{
      "rankingPts":982.45,
      "confederationID":"CONCACAF",
      "flagCode":"bm"
   },
   "Bhutan":{
      "rankingPts":867.86,
      "confederationID":"AFC",
      "flagCode":"bt"
   },
   "Bolivia":{
      "rankingPts":1329.56,
      "confederationID":"CONMEBOL",
      "flagCode":"bo"
   },
   "Bosnia and Herzegovina":{
      "rankingPts":1362.37,
      "confederationID":"UEFA",
      "flagCode":"ba"
   },
   "Botswana":{
      "rankingPts":1084.56,
      "confederationID":"CAF",
      "flagCode":"bw"
   },
   "Brazil":{
      "rankingPts":1760.46,
      "confederationID":"CONMEBOL",
      "flagCode":"br"
   },
   "British Virgin Islands":{
      "rankingPts":776.54,
      "confederationID":"CONCACAF",
      "flagCode":"vg"
   },
   "Brunei":{
      "rankingPts":875.78,
      "confederationID":"AFC",
      "flagCode":"bn"
   },
   "Bulgaria":{
      "rankingPts":1272.19,
      "confederationID":"UEFA",
      "flagCode":"bg"
   },
   "Burkina Faso":{
      "rankingPts":1404.81,
      "confederationID":"CAF",
      "flagCode":"bf"
   },
   "Burundi":{
      "rankingPts":1060.22,
      "confederationID":"CAF",
      "flagCode":"bi"
   },
   "Cambodia":{
      "rankingPts":911.54,
      "confederationID":"AFC",
      "flagCode":"kh"
   },
   "Cameroon":{
      "rankingPts":1440.43,
      "confederationID":"CAF",
      "flagCode":"cm"
   },
   "Canada":{
      "rankingPts":1563.26,
      "confederationID":"CONCACAF",
      "flagCode":"ca"
   },
   "Cape Verde":{
      "rankingPts":1367.95,
      "confederationID":"CAF",
      "flagCode":"cv"
   },
   "Cayman Islands":{
      "rankingPts":851.74,
      "confederationID":"CONCACAF",
      "flagCode":"ky"
   },
   "Central African Republic":{
      "rankingPts":1083.57,
      "confederationID":"CAF",
      "flagCode":"cf"
   },
   "Chad":{
      "rankingPts":914.65,
      "confederationID":"CAF",
      "flagCode":"td"
   },
   "Chile":{
      "rankingPts":1457.84,
      "confederationID":"CONMEBOL",
      "flagCode":"cl"
   },
   "China PR":{
      "rankingPts":1249.06,
      "confederationID":"AFC",
      "flagCode":"cn"
   },
   "Chinese Taipei":{
      "rankingPts":938.21,
      "confederationID":"AFC",
      "flagCode":"tw"
   },
   "Colombia":{
      "rankingPts":1705.1,
      "confederationID":"CONMEBOL",
      "flagCode":"co"
   },
   "Comoros":{
      "rankingPts":1189.75,
      "confederationID":"CAF",
      "flagCode":"km"
   },
   "Congo":{
      "rankingPts":1105.96,
      "confederationID":"CAF",
      "flagCode":"cg"
   },
   "Cook Islands":{
      "rankingPts":877.53,
      "confederationID":"OFC",
      "flagCode":"ck"
   },
   "Costa Rica":{
      "rankingPts":1462.23,
      "confederationID":"CONCACAF",
      "flagCode":"cr"
   },
   "Croatia":{
      "rankingPts":1716.88,
      "confederationID":"UEFA",
      "flagCode":"hr"
   },
   "Cuba":{
      "rankingPts":980.49,
      "confederationID":"CONCACAF",
      "flagCode":"cu"
   },
   "Curaçao":{
      "rankingPts":1304.13,
      "confederationID":"CONCACAF",
      "flagCode":"cw"
   },
   "Cyprus":{
      "rankingPts":1128.5,
      "confederationID":"UEFA",
      "flagCode":"cy"
   },
   "Czech Republic":{
      "rankingPts":1487,
      "confederationID":"UEFA",
      "flagCode":"cz"
   },
   "Denmark":{
      "rankingPts":1616.75,
      "confederationID":"UEFA",
      "flagCode":"dk"
   },
   "Djibouti":{
      "rankingPts":847.89,
      "confederationID":"CAF",
      "flagCode":"dj"
   },
   "Dominica":{
      "rankingPts":901.37,
      "confederationID":"CONCACAF",
      "flagCode":"dm"
   },
   "Dominican Republic":{
      "rankingPts":1077.49,
      "confederationID":"CONCACAF",
      "flagCode":"do"
   },
   "DR Congo":{
      "rankingPts":1442.5,
      "confederationID":"CAF",
      "flagCode":"cd"
   },
   "Ecuador":{
      "rankingPts":1594.05,
      "confederationID":"CONMEBOL",
      "flagCode":"ec"
   },
   "Egypt":{
      "rankingPts":1520.68,
      "confederationID":"CAF",
      "flagCode":"eg"
   },
   "El Salvador":{
      "rankingPts":1220.88,
      "confederationID":"CONCACAF",
      "flagCode":"sv"
   },
   "England":{
      "rankingPts":1834.12,
      "confederationID":"UEFA",
      "flagCode":"gb-eng"
   },
   "Equatorial Guinea":{
      "rankingPts":1229.09,
      "confederationID":"CAF",
      "flagCode":"gq"
   },
   "Eritrea":{
      "rankingPts":832,
      "confederationID":"CAF",
      "flagCode":"er"
   },
   "Estonia":{
      "rankingPts":1123.11,
      "confederationID":"UEFA",
      "flagCode":"ee"
   },
   "Eswatini":{
      "rankingPts":1010.52,
      "confederationID":"CAF",
      "flagCode":"sz"
   },
   "Ethiopia":{
      "rankingPts":1055.36,
      "confederationID":"CAF",
      "flagCode":"et"
   },
   "Faroe Islands":{
      "rankingPts":1135.42,
      "confederationID":"UEFA",
      "flagCode":"fo"
   },
   "Fiji":{
      "rankingPts":1026.99,
      "confederationID":"OFC",
      "flagCode":"fj"
   },
   "Finland":{
      "rankingPts":1341.81,
      "confederationID":"UEFA",
      "flagCode":"fi"
   },
   "France":{
      "rankingPts":1870,
      "confederationID":"UEFA",
      "flagCode":"fr"
   },
   "Gabon":{
      "rankingPts":1321.25,
      "confederationID":"CAF",
      "flagCode":"ga"
   },
   "Gambia":{
      "rankingPts":1161.55,
      "confederationID":"CAF",
      "flagCode":"gm"
   },
   "Georgia":{
      "rankingPts":1347.88,
      "confederationID":"UEFA",
      "flagCode":"ge"
   },
   "Germany":{
      "rankingPts":1724.15,
      "confederationID":"UEFA",
      "flagCode":"de"
   },
   "Ghana":{
      "rankingPts":1351.09,
      "confederationID":"CAF",
      "flagCode":"gh"
   },
   "Gibraltar":{
      "rankingPts":818.03,
      "confederationID":"UEFA",
      "flagCode":"gi"
   },
   "Greece":{
      "rankingPts":1480.38,
      "confederationID":"UEFA",
      "flagCode":"gr"
   },
   "Grenada":{
      "rankingPts":989.59,
      "confederationID":"CONCACAF",
      "flagCode":"gd"
   },
   "Guam":{
      "rankingPts":823.08,
      "confederationID":"AFC",
      "flagCode":"gu"
   },
   "Guatemala":{
      "rankingPts":1255.78,
      "confederationID":"CONCACAF",
      "flagCode":"gt"
   },
   "Guinea":{
      "rankingPts":1307.05,
      "confederationID":"CAF",
      "flagCode":"gn"
   },
   "Guinea-Bissau":{
      "rankingPts":1108.09,
      "confederationID":"CAF",
      "flagCode":"gw"
   },
   "Guyana":{
      "rankingPts":1041.9,
      "confederationID":"CONCACAF",
      "flagCode":"gy"
   },
   "Haiti":{
      "rankingPts":1302.89,
      "confederationID":"CONCACAF",
      "flagCode":"ht"
   },
   "Honduras":{
      "rankingPts":1381.55,
      "confederationID":"CONCACAF",
      "flagCode":"hn"
   },
   "Hong Kong":{
      "rankingPts":1038.14,
      "confederationID":"AFC",
      "flagCode":"hk"
   },
   "Hungary":{
      "rankingPts":1496.29,
      "confederationID":"UEFA",
      "flagCode":"hu"
   },
   "Iceland":{
      "rankingPts":1344.72,
      "confederationID":"UEFA",
      "flagCode":"is"
   },
   "India":{
      "rankingPts":1079.52,
      "confederationID":"AFC",
      "flagCode":"in"
   },
   "Indonesia":{
      "rankingPts":1144.73,
      "confederationID":"AFC",
      "flagCode":"id"
   },
   "Iran":{
      "rankingPts":1617.02,
      "confederationID":"AFC",
      "flagCode":"ir"
   },
   "Iraq":{
      "rankingPts":1438.92,
      "confederationID":"AFC",
      "flagCode":"iq"
   },
   "Israel":{
      "rankingPts":1328.14,
      "confederationID":"UEFA",
      "flagCode":"il"
   },
   "Italy":{
      "rankingPts":1702.06,
      "confederationID":"UEFA",
      "flagCode":"it"
   },
   "Cote d'Ivoire":{
      "rankingPts":1489.59,
      "confederationID":"CAF",
      "flagCode":"ci"
   },
   "Jamaica":{
      "rankingPts":1361.03,
      "confederationID":"CONCACAF",
      "flagCode":"jm"
   },
   "Japan":{
      "rankingPts":1650.12,
      "confederationID":"AFC",
      "flagCode":"jp"
   },
   "Jordan":{
      "rankingPts":1377.66,
      "confederationID":"AFC",
      "flagCode":"jo"
   },
   "Kazakhstan":{
      "rankingPts":1173,
      "confederationID":"UEFA",
      "flagCode":"kz"
   },
   "Kenya":{
      "rankingPts":1179.54,
      "confederationID":"CAF",
      "flagCode":"ke"
   },
   "Kosovo":{
      "rankingPts":1308.84,
      "confederationID":"UEFA",
      "flagCode":"xk"
   },
   "Kuwait":{
      "rankingPts":1103.25,
      "confederationID":"AFC",
      "flagCode":"kw"
   },
   "Kyrgyzstan":{
      "rankingPts":1201.22,
      "confederationID":"AFC",
      "flagCode":"kg"
   },
   "Laos":{
      "rankingPts":871.16,
      "confederationID":"AFC",
      "flagCode":"la"
   },
   "Latvia":{
      "rankingPts":1082.68,
      "confederationID":"UEFA",
      "flagCode":"lv"
   },
   "Lebanon":{
      "rankingPts":1190.64,
      "confederationID":"AFC",
      "flagCode":"lb"
   },
   "Lesotho":{
      "rankingPts":1065.97,
      "confederationID":"CAF",
      "flagCode":"ls"
   },
   "Liberia":{
      "rankingPts":1081.46,
      "confederationID":"CAF",
      "flagCode":"lr"
   },
   "Libya":{
      "rankingPts":1182.78,
      "confederationID":"CAF",
      "flagCode":"ly"
   },
   "Liechtenstein":{
      "rankingPts":799.8,
      "confederationID":"UEFA",
      "flagCode":"li"
   },
   "Lithuania":{
      "rankingPts":1056.34,
      "confederationID":"UEFA",
      "flagCode":"lt"
   },
   "Luxembourg":{
      "rankingPts":1218.91,
      "confederationID":"UEFA",
      "flagCode":"lu"
   },
   "Macau":{
      "rankingPts":865.29,
      "confederationID":"AFC",
      "flagCode":"mo"
   },
   "North Macedonia":{
      "rankingPts":1378.57,
      "confederationID":"UEFA",
      "flagCode":"mk"
   },
   "Madagascar":{
      "rankingPts":1198.87,
      "confederationID":"CAF",
      "flagCode":"mg"
   },
   "Malawi":{
      "rankingPts":1133.75,
      "confederationID":"CAF",
      "flagCode":"mw"
   },
   "Malaysia":{
      "rankingPts":1168.41,
      "confederationID":"AFC",
      "flagCode":"my"
   },
   "Maldives":{
      "rankingPts":945.02,
      "confederationID":"AFC",
      "flagCode":"mv"
   },
   "Mali":{
      "rankingPts":1455.03,
      "confederationID":"CAF",
      "flagCode":"ml"
   },
   "Malta":{
      "rankingPts":996.59,
      "confederationID":"UEFA",
      "flagCode":"mt"
   },
   "Mauritania":{
      "rankingPts":1174.19,
      "confederationID":"CAF",
      "flagCode":"mr"
   },
   "Mauritius":{
      "rankingPts":915.51,
      "confederationID":"CAF",
      "flagCode":"mu"
   },
   "Mexico":{
      "rankingPts":1669.14,
      "confederationID":"CONCACAF",
      "flagCode":"mx"
   },
   "Moldova":{
      "rankingPts":1012.64,
      "confederationID":"UEFA",
      "flagCode":"md"
   },
   "Mongolia":{
      "rankingPts":879.75,
      "confederationID":"AFC",
      "flagCode":"mn"
   },
   "Montenegro":{
      "rankingPts":1297.09,
      "confederationID":"UEFA",
      "flagCode":"me"
   },
   "Montserrat":{
      "rankingPts":916.75,
      "confederationID":"CONCACAF",
      "flagCode":"ms"
   },
   "Morocco":{
      "rankingPts":1713.12,
      "confederationID":"CAF",
      "flagCode":"ma"
   },
   "Mozambique":{
      "rankingPts":1223.48,
      "confederationID":"CAF",
      "flagCode":"mz"
   },
   "Myanmar":{
      "rankingPts":990.81,
      "confederationID":"AFC",
      "flagCode":"mm"
   },
   "Namibia":{
      "rankingPts":1153.22,
      "confederationID":"CAF",
      "flagCode":"na"
   },
   "Nepal":{
      "rankingPts":902.44,
      "confederationID":"AFC",
      "flagCode":"np"
   },
   "Netherlands":{
      "rankingPts":1756.27,
      "confederationID":"UEFA",
      "flagCode":"nl"
   },
   "New Caledonia":{
      "rankingPts":1042.62,
      "confederationID":"OFC",
      "flagCode":"nc"
   },
   "New Zealand":{
      "rankingPts":1276.93,
      "confederationID":"OFC",
      "flagCode":"nz"
   },
   "Nicaragua":{
      "rankingPts":1108.46,
      "confederationID":"CONCACAF",
      "flagCode":"ni"
   },
   "Niger":{
      "rankingPts":1185.09,
      "confederationID":"CAF",
      "flagCode":"ne"
   },
   "Nigeria":{
      "rankingPts":1502.46,
      "confederationID":"CAF",
      "flagCode":"ng"
   },
   "North Korea":{
      "rankingPts":1151.05,
      "confederationID":"AFC",
      "flagCode":"kp"
   },
   "Northern Ireland":{
      "rankingPts":1366.02,
      "confederationID":"UEFA",
      "flagCode":"gb-nir"
   },
   "Norway":{
      "rankingPts":1553.14,
      "confederationID":"UEFA",
      "flagCode":"no"
   },
   "Oman":{
      "rankingPts":1312.45,
      "confederationID":"AFC",
      "flagCode":"om"
   },
   "Pakistan":{
      "rankingPts":833.16,
      "confederationID":"AFC",
      "flagCode":"pk"
   },
   "Palestine":{
      "rankingPts":1230.55,
      "confederationID":"AFC",
      "flagCode":"ps"
   },
   "Panama":{
      "rankingPts":1546.2,
      "confederationID":"CONCACAF",
      "flagCode":"pa"
   },
   "Papua New Guinea":{
      "rankingPts":977.77,
      "confederationID":"OFC",
      "flagCode":"pg"
   },
   "Paraguay":{
      "rankingPts":1508.11,
      "confederationID":"CONMEBOL",
      "flagCode":"py"
   },
   "Peru":{
      "rankingPts":1459.57,
      "confederationID":"CONMEBOL",
      "flagCode":"pe"
   },
   "Philippines":{
      "rankingPts":1090.95,
      "confederationID":"AFC",
      "flagCode":"ph"
   },
   "Poland":{
      "rankingPts":1532.04,
      "confederationID":"UEFA",
      "flagCode":"pl"
   },
   "Portugal":{
      "rankingPts":1760.38,
      "confederationID":"UEFA",
      "flagCode":"pt"
   },
   "Puerto Rico":{
      "rankingPts":1020.07,
      "confederationID":"CONCACAF",
      "flagCode":"pr"
   },
   "Qatar":{
      "rankingPts":1461.6,
      "confederationID":"AFC",
      "flagCode":"qa"
   },
   "Republic of Ireland":{
      "rankingPts":1436.04,
      "confederationID":"UEFA",
      "flagCode":"ie"
   },
   "Romania":{
      "rankingPts":1465.78,
      "confederationID":"UEFA",
      "flagCode":"ro"
   },
   "Russia":{
      "rankingPts":1524.52,
      "confederationID":"UEFA",
      "flagCode":"ru"
   },
   "Rwanda":{
      "rankingPts":1117.78,
      "confederationID":"CAF",
      "flagCode":"rw"
   },
   "Saint Kitts and Nevis":{
      "rankingPts":1035.25,
      "confederationID":"CONCACAF",
      "flagCode":"kn"
   },
   "Saint Lucia":{
      "rankingPts":980.28,
      "confederationID":"CONCACAF",
      "flagCode":"lc"
   },
   "Saint Vincent and the Grenadines":{
      "rankingPts":963.74,
      "confederationID":"CONCACAF",
      "flagCode":"vc"
   },
   "Samoa":{
      "rankingPts":876.41,
      "confederationID":"OFC",
      "flagCode":"ws"
   },
   "San Marino":{
      "rankingPts":726.03,
      "confederationID":"UEFA",
      "flagCode":"sm"
   },
   "São Tomé and Príncipe":{
      "rankingPts":871.63,
      "confederationID":"CAF",
      "flagCode":"st"
   },
   "Saudi Arabia":{
      "rankingPts":1428.74,
      "confederationID":"AFC",
      "flagCode":"sa"
   },
   "Scotland":{
      "rankingPts":1506.77,
      "confederationID":"UEFA",
      "flagCode":"gb-sct"
   },
   "Senegal":{
      "rankingPts":1648.07,
      "confederationID":"CAF",
      "flagCode":"sn"
   },
   "Serbia":{
      "rankingPts":1506.34,
      "confederationID":"UEFA",
      "flagCode":"rs"
   },
   "Seychelles":{
      "rankingPts":805.33,
      "confederationID":"CAF",
      "flagCode":"sc"
   },
   "Sierra Leone":{
      "rankingPts":1149.1,
      "confederationID":"CAF",
      "flagCode":"sl"
   },
   "Singapore":{
      "rankingPts":1040.43,
      "confederationID":"AFC",
      "flagCode":"sg"
   },
   "Slovakia":{
      "rankingPts":1485.65,
      "confederationID":"UEFA",
      "flagCode":"sk"
   },
   "Slovenia":{
      "rankingPts":1447.31,
      "confederationID":"UEFA",
      "flagCode":"si"
   },
   "Solomon Islands":{
      "rankingPts":1037.11,
      "confederationID":"OFC",
      "flagCode":"sb"
   },
   "Somalia":{
      "rankingPts":831.27,
      "confederationID":"CAF",
      "flagCode":"so"
   },
   "South Africa":{
      "rankingPts":1426.73,
      "confederationID":"CAF",
      "flagCode":"za"
   },
   "South Korea":{
      "rankingPts":1599.45,
      "confederationID":"AFC",
      "flagCode":"kr"
   },
   "South Sudan":{
      "rankingPts":978.7,
      "confederationID":"CAF",
      "flagCode":"ss"
   },
   "Spain":{
      "rankingPts":1877.18,
      "confederationID":"UEFA",
      "flagCode":"es"
   },
   "Sri Lanka":{
      "rankingPts":857.4,
      "confederationID":"AFC",
      "flagCode":"lk"
   },
   "Sudan":{
      "rankingPts":1153.56,
      "confederationID":"CAF",
      "flagCode":"sd"
   },
   "Suriname":{
      "rankingPts":1130.53,
      "confederationID":"CONCACAF",
      "flagCode":"sr"
   },
   "Sweden":{
      "rankingPts":1487.13,
      "confederationID":"UEFA",
      "flagCode":"se"
   },
   "Switzerland":{
      "rankingPts":1654.69,
      "confederationID":"UEFA",
      "flagCode":"ch"
   },
   "Syria":{
      "rankingPts":1278.1,
      "confederationID":"AFC",
      "flagCode":"sy"
   },
   "Tahiti":{
      "rankingPts":1019.04,
      "confederationID":"OFC",
      "flagCode":"pf"
   },
   "Tajikistan":{
      "rankingPts":1224.93,
      "confederationID":"AFC",
      "flagCode":"tj"
   },
   "Tanzania":{
      "rankingPts":1181.22,
      "confederationID":"CAF",
      "flagCode":"tz"
   },
   "Thailand":{
      "rankingPts":1243.27,
      "confederationID":"AFC",
      "flagCode":"th"
   },
   "Timor-Leste":{
      "rankingPts":835.55,
      "confederationID":"AFC",
      "flagCode":"tl"
   },
   "Togo":{
      "rankingPts":1140.35,
      "confederationID":"CAF",
      "flagCode":"tg"
   },
   "Tonga":{
      "rankingPts":835.64,
      "confederationID":"OFC",
      "flagCode":"to"
   },
   "Trinidad and Tobago":{
      "rankingPts":1221.74,
      "confederationID":"CONCACAF",
      "flagCode":"tt"
   },
   "Tunisia":{
      "rankingPts":1497.13,
      "confederationID":"CAF",
      "flagCode":"tn"
   },
   "Turkey":{
      "rankingPts":1582.69,
      "confederationID":"UEFA",
      "flagCode":"tr"
   },
   "Turkmenistan":{
      "rankingPts":1087.52,
      "confederationID":"AFC",
      "flagCode":"tm"
   },
   "Turks and Caicos Islands":{
      "rankingPts":803.98,
      "confederationID":"CONCACAF",
      "flagCode":"tc"
   },
   "Uganda":{
      "rankingPts":1288.01,
      "confederationID":"CAF",
      "flagCode":"ug"
   },
   "Ukraine":{
      "rankingPts":1557.47,
      "confederationID":"UEFA",
      "flagCode":"ua"
   },
   "United Arab Emirates":{
      "rankingPts":1369.71,
      "confederationID":"AFC",
      "flagCode":"ae"
   },
   "United States":{
      "rankingPts":1686.79,
      "confederationID":"CONCACAF",
      "flagCode":"us"
   },
   "Uruguay":{
      "rankingPts":1667.71,
      "confederationID":"CONMEBOL",
      "flagCode":"uy"
   },
   "U.S. Virgin Islands":{
      "rankingPts":776.6,
      "confederationID":"CONCACAF",
      "flagCode":"vi"
   },
   "Uzbekistan":{
      "rankingPts":1462.03,
      "confederationID":"AFC",
      "flagCode":"uz"
   },
   "Vanuatu":{
      "rankingPts":999.61,
      "confederationID":"OFC",
      "flagCode":"vu"
   },
   "Venezuela":{
      "rankingPts":1461.11,
      "confederationID":"CONMEBOL",
      "flagCode":"ve"
   },
   "Vietnam":{
      "rankingPts":1189.51,
      "confederationID":"AFC",
      "flagCode":"vn"
   },
   "Wales":{
      "rankingPts":1529.71,
      "confederationID":"UEFA",
      "flagCode":"gb-wls"
   },
   "Yemen":{
      "rankingPts":1048.83,
      "confederationID":"AFC",
      "flagCode":"ye"
   },
   "Zambia":{
      "rankingPts":1260.06,
      "confederationID":"CAF",
      "flagCode":"zm"
   },
   "Zimbabwe":{
      "rankingPts":1123.69,
      "confederationID":"CAF",
      "flagCode":"zw"
   }
}